oprouter/__init__.py
oprouter/__main__.py
oprouter/core/__init__.py
oprouter/core/config.py
oprouter/core/logger.py
oprouter/interfaces/__init__.py
oprouter/interfaces/api_client.py
oprouter/interfaces/storage.py
oprouter/services/__init__.py
oprouter/services/api_client.py
oprouter/storage/__init__.py
oprouter/storage/conversation.py
oprouter/ui/__init__.py
oprouter/ui/cli.py
oprouter/ui/emoji_utils.py
oprouter/utils/__init__.py
oprouter/utils/conversation_analyzer.py
oprouter/utils/rate_limiter.py
oprouter/utils/text_formatter.py
oprouter/utils/token_counter.py
oprouter/utils/validators.py
oprouter-1.0.1.dist-info/licenses/LICENSE
oprouter-1.0.1.dist-info/METADATA
oprouter-1.0.1.dist-info/WHEEL
oprouter-1.0.1.dist-info/entry_points.txt
oprouter-1.0.1.dist-info/top_level.txt
oprouter-1.0.1.dist-info/RECORD
